LICENSE
MANIFEST.in
README.rst
setup.py
angular_dynamic_forms/__init__.py
angular_dynamic_forms/autocomplete.py
angular_dynamic_forms/decorators.py
angular_dynamic_forms/foreign_key.py
angular_dynamic_forms/linked_form.py
angular_dynamic_forms/logging.py
angular_dynamic_forms/rest.py
angular_dynamic_forms/locale/cs/LC_MESSAGES/django.mo
angular_dynamic_forms/locale/cs/LC_MESSAGES/django.po
django_angular_dynamic_forms.egg-info/PKG-INFO
django_angular_dynamic_forms.egg-info/SOURCES.txt
django_angular_dynamic_forms.egg-info/dependency_links.txt
django_angular_dynamic_forms.egg-info/requires.txt
django_angular_dynamic_forms.egg-info/top_level.txt