Metadata-Version: 1.1
Name: django-angular-dynamic-forms
Version: 6.1.3
Summary: Django Rest Framework meets Angular 5 material.io dynamic forms - rapid development of create and edit dialogs
Home-page: https://github.com/mesemus/django-angular-dynamic-forms
Author: Mirek Simek
Author-email: miroslav.simek@gmail.com
License: MIT
Keywords: django-rest-framework django angular2 forms ng-dynamic-forms
Platform: UNKNOWN
Classifier: Development Status :: 3 - Alpha
Classifier: Intended Audience :: Developers
Classifier: Topic :: Software Development :: Libraries
Classifier: License :: OSI Approved :: MIT License
Classifier: Programming Language :: Python :: 3.4
Classifier: Programming Language :: Python :: 3.5
Classifier: Programming Language :: Python :: 3.6
